auto_load_cfg.py
hwpylib-0.1.0.dist-info/METADATA
hwpylib-0.1.0.dist-info/WHEEL
hwpylib-0.1.0.dist-info/top_level.txt
hwpylib-0.1.0.dist-info/RECORD
