Metadata-Version: 2.4
Name: hwpylib
Version: 0.1.0
Summary: 通过装饰器来读取env文件，并自动给函数添加环境变量
Requires-Python: >=3.13
Requires-Dist: loguru>=0.7.3
Requires-Dist: pymysql>=1.1.2
Requires-Dist: python-decouple>=3.8
